AUTHORS.rst
CONTRIBUTING.rst
HISTORY.rst
LICENSE
MANIFEST.in
README.rst
setup.cfg
setup.py
docs/Makefile
docs/authors.rst
docs/conf.py
docs/contributing.rst
docs/history.rst
docs/index.rst
docs/installation.rst
docs/make.bat
docs/usage.rst
ka_lite_gtk.egg-info/PKG-INFO
ka_lite_gtk.egg-info/SOURCES.txt
ka_lite_gtk.egg-info/dependency_links.txt
ka_lite_gtk.egg-info/entry_points.txt
ka_lite_gtk.egg-info/not-zip-safe
ka_lite_gtk.egg-info/pbr.json
ka_lite_gtk.egg-info/top_level.txt
kalite_gtk/__init__.py
kalite_gtk/__main__.py
kalite_gtk/cli.py
kalite_gtk/exceptions.py
kalite_gtk/mainwindow.py
kalite_gtk/validators.py
kalite_gtk/glade/ka-icon.png
kalite_gtk/glade/ka-lite-logo.png
kalite_gtk/glade/mainwindow.glade
kalite_gtk/glade/mainwindow.glade~
tests/__init__.py
tests/test_kalite_gtk.py