Metadata-Version: 1.1
Name: ka-lite-gtk
Version: 0.3a2
Summary: User interface for KA Lite (GTK3)
Home-page: https://github.com/learningequality/ka-lite-gtk
Author: Foundation for Learning Equality
Author-email: info@learningequality.org
License: MIT
Keywords: ka-lite-gtk,ka lite,ka-lite
Platform: UNKNOWN
Classifier: Development Status :: 4 - Beta
Classifier: Intended Audience :: Developers
Classifier: License :: OSI Approved :: MIT License
Classifier: Natural Language :: English
Classifier: Programming Language :: Python :: 2
Classifier: Programming Language :: Python :: 2.7
Classifier: Programming Language :: Python :: 3
Classifier: Programming Language :: Python :: 3.3
Classifier: Programming Language :: Python :: 3.4
